qqutils/__init__.py
qqutils/asyncutils.py
qqutils/bloom_filter.py
qqutils/cert-qqutils.pem
qqutils/commutils.py
qqutils/cryptutils.py
qqutils/datautils.py
qqutils/dateutils.py
qqutils/dbgutils.py
qqutils/dsutils.py
qqutils/funcutils.py
qqutils/inspectutils.py
qqutils/key-qqutils.pem
qqutils/logutils.py
qqutils/netutils.py
qqutils/objutils.py
qqutils/osutils.py
qqutils/sqliteutils.py
qqutils/stringutils.py
qqutils/threadutils.py
qqutils/urlutils.py
qqutils/version.py
qqutils-0.0.89.dist-info/licenses/LICENSE
qqutils-0.0.89.dist-info/METADATA
qqutils-0.0.89.dist-info/WHEEL
qqutils-0.0.89.dist-info/top_level.txt
qqutils-0.0.89.dist-info/RECORD
